genga/__init__.py
genga/functions.py
genga-0.1.0.dist-info/licenses/LICENSE.txt
genga-0.1.0.dist-info/METADATA
genga-0.1.0.dist-info/WHEEL
genga-0.1.0.dist-info/top_level.txt
genga-0.1.0.dist-info/RECORD
