Metadata-Version: 2.4
Name: genga
Version: 0.1.0
Summary: A GWCNA + Co-expression networks analysis tool for gene expression analysis.
Author-email: Andres Santiago Martinez <as.martinez@uniandes.edu.co>
Project-URL: Homepage, https://github.com/neurogen-uniandes/networks
Project-URL: Issues, https://github.com/neurogen-uniandes/networks/issues
Keywords: genga,GWCNA,graph
Classifier: Development Status :: 3 - Alpha
Classifier: Intended Audience :: Developers
Classifier: License :: OSI Approved :: MIT License
Classifier: Programming Language :: Python :: 3
Classifier: Programming Language :: Python :: 3.8
Classifier: Programming Language :: Python :: 3.9
Classifier: Programming Language :: Python :: 3.10
Classifier: Programming Language :: Python :: 3.11
Classifier: Programming Language :: Python :: 3.12
Classifier: Operating System :: OS Independent
Classifier: Topic :: Software Development :: Libraries :: Python Modules
Requires-Python: >=3.8
License-File: LICENSE.txt
Dynamic: license-file
